{
    "314211309": {
        "test_results": {
            "question1": "dev",
            "question2": "remote",
            "question3": "beginner"
        },
        "name": "danya",
        "age": "21",
        "number": "+79157405181"
    },
    "998306621": {
        "name": "Елизавета",
        "age": "19",
        "number": "79021807727",
        "test_results": {
            "question1": "dev",
            "question2": "remote",
            "question3": "beginner"
        }
    },
    "452514399": {
        "name": "Николай",
        "age": "20",
        "city": "Самара"
    },
    "2047214040": {
        "name": "Юлия",
        "age": "1000",
        "number": "1111111111454"
    }
}